dhd/__init__.py
dhd/city.py
dhd/cli.py
dhd/connect.py
dhd/evolve.py
dhd/exceptions.py
dhd/features.py
dhd/load.py
dhd/logs.py
dhd/modify.py
dhd/plot.py
dhd/utils.py
dhd-0.1.3.dist-info/AUTHORS.rst
dhd-0.1.3.dist-info/LICENSE
dhd-0.1.3.dist-info/METADATA
dhd-0.1.3.dist-info/WHEEL
dhd-0.1.3.dist-info/top_level.txt
dhd-0.1.3.dist-info/RECORD
