Metadata-Version: 2.1
Name: dhd
Version: 0.1.3
Summary: Graph theory and evolutionary algorithm applied to city district heating network design
Home-page: https://gitlab.com/crem-repository/dhd
Author: CREM
Author-email: info@crem.ch
License: Apache Software License 2.0
Keywords: dhd
Platform: UNKNOWN
Classifier: Development Status :: 2 - Pre-Alpha
Classifier: Intended Audience :: Developers
Classifier: License :: OSI Approved :: Apache Software License
Classifier: Natural Language :: English
Classifier: Programming Language :: Python :: 3
Classifier: Programming Language :: Python :: 3.4
Classifier: Programming Language :: Python :: 3.5
Classifier: Programming Language :: Python :: 3.6
Classifier: Programming Language :: Python :: 3.7
Requires-Dist: sphinx (>=1.8)
Requires-Dist: sphinxcontrib-napoleon
Requires-Dist: click (>=6.0)
Requires-Dist: osmnx (>=0.9)
